README.md
setup.cfg
setup.py
obify/__init__.py
obify/heap.py
obify/util.py
obify.egg-info/PKG-INFO
obify.egg-info/SOURCES.txt
obify.egg-info/dependency_links.txt
obify.egg-info/top_level.txt