Metadata-Version: 2.1
Name: obify
Version: 0.0.3
Summary: This library provides a set of data structures that will work on python objects similar to collections framework in java
Home-page: https://github.com/amanchourasiya/obify
Author: Aman Chourasiya
Author-email: aman@amanchourasiya.com
License: GNU GPL-v3
Download-URL: https://github.com/amanchourasiya/obify/archive/refs/tags/v0.0.3.tar.gz
Keywords: Collections,Objects,Data structures
Platform: UNKNOWN
Classifier: Development Status :: 3 - Alpha
Classifier: Intended Audience :: Developers
Classifier: Topic :: Software Development :: Build Tools
Classifier: License :: OSI Approved :: GNU General Public License (GPL)
Classifier: Programming Language :: Python :: 3
